[
    {
        "first_stop":5.0,
        "last_stop":284.0,
        "total_duration":135.0,
        "mean_of_mean_gradient":0.0032805708,
        "max_of_max_gradient":0.4920856229,
        "total_weight_change":0.9841712458,
        "skewness":-4.6326579476,
        "kurtosis":19.4623069512,
        "start_time":5.0,
        "end_time":16.0,
        "duration":12.0,
        "shaking_duration":7.0,
        "mean_gradient":0.0820142705,
        "max_gradient":0.4920856229,
        "weight_change":0.9841712458
    },
    {
        "first_stop":5.0,
        "last_stop":284.0,
        "total_duration":135.0,
        "mean_of_mean_gradient":0.0032805708,
        "max_of_max_gradient":0.4920856229,
        "total_weight_change":0.9841712458,
        "skewness":-4.6326579476,
        "kurtosis":19.4623069512,
        "start_time":16.0,
        "end_time":24.0,
        "duration":9.0,
        "shaking_duration":5.0,
        "mean_gradient":0.0,
        "max_gradient":0.0,
        "weight_change":0.0
    },
    {
        "first_stop":5.0,
        "last_stop":284.0,
        "total_duration":135.0,
        "mean_of_mean_gradient":0.0032805708,
        "max_of_max_gradient":0.4920856229,
        "total_weight_change":0.9841712458,
        "skewness":-4.6326579476,
        "kurtosis":19.4623069512,
        "start_time":24.0,
        "end_time":34.0,
        "duration":11.0,
        "shaking_duration":6.0,
        "mean_gradient":0.0,
        "max_gradient":0.0,
        "weight_change":0.0
    },
    {
        "first_stop":5.0,
        "last_stop":284.0,
        "total_duration":135.0,
        "mean_of_mean_gradient":0.0032805708,
        "max_of_max_gradient":0.4920856229,
        "total_weight_change":0.9841712458,
        "skewness":-4.6326579476,
        "kurtosis":19.4623069512,
        "start_time":34.0,
        "end_time":46.0,
        "duration":13.0,
        "shaking_duration":9.0,
        "mean_gradient":0.0,
        "max_gradient":0.0,
        "weight_change":0.0
    },
    {
        "first_stop":5.0,
        "last_stop":284.0,
        "total_duration":135.0,
        "mean_of_mean_gradient":0.0032805708,
        "max_of_max_gradient":0.4920856229,
        "total_weight_change":0.9841712458,
        "skewness":-4.6326579476,
        "kurtosis":19.4623069512,
        "start_time":46.0,
        "end_time":58.0,
        "duration":13.0,
        "shaking_duration":6.0,
        "mean_gradient":0.0,
        "max_gradient":0.0,
        "weight_change":0.0
    },
    {
        "first_stop":5.0,
        "last_stop":284.0,
        "total_duration":135.0,
        "mean_of_mean_gradient":0.0032805708,
        "max_of_max_gradient":0.4920856229,
        "total_weight_change":0.9841712458,
        "skewness":-4.6326579476,
        "kurtosis":19.4623069512,
        "start_time":58.0,
        "end_time":79.0,
        "duration":22.0,
        "shaking_duration":16.0,
        "mean_gradient":0.0,
        "max_gradient":0.0,
        "weight_change":0.0
    },
    {
        "first_stop":5.0,
        "last_stop":284.0,
        "total_duration":135.0,
        "mean_of_mean_gradient":0.0032805708,
        "max_of_max_gradient":0.4920856229,
        "total_weight_change":0.9841712458,
        "skewness":-4.6326579476,
        "kurtosis":19.4623069512,
        "start_time":79.0,
        "end_time":89.0,
        "duration":11.0,
        "shaking_duration":4.0,
        "mean_gradient":0.0,
        "max_gradient":0.0,
        "weight_change":0.0
    },
    {
        "first_stop":5.0,
        "last_stop":284.0,
        "total_duration":135.0,
        "mean_of_mean_gradient":0.0032805708,
        "max_of_max_gradient":0.4920856229,
        "total_weight_change":0.9841712458,
        "skewness":-4.6326579476,
        "kurtosis":19.4623069512,
        "start_time":89.0,
        "end_time":99.0,
        "duration":11.0,
        "shaking_duration":4.0,
        "mean_gradient":0.0,
        "max_gradient":0.0,
        "weight_change":0.0
    },
    {
        "first_stop":5.0,
        "last_stop":284.0,
        "total_duration":135.0,
        "mean_of_mean_gradient":0.0032805708,
        "max_of_max_gradient":0.4920856229,
        "total_weight_change":0.9841712458,
        "skewness":-4.6326579476,
        "kurtosis":19.4623069512,
        "start_time":99.0,
        "end_time":111.0,
        "duration":13.0,
        "shaking_duration":6.0,
        "mean_gradient":0.0,
        "max_gradient":0.0,
        "weight_change":0.0
    },
    {
        "first_stop":5.0,
        "last_stop":284.0,
        "total_duration":135.0,
        "mean_of_mean_gradient":0.0032805708,
        "max_of_max_gradient":0.4920856229,
        "total_weight_change":0.9841712458,
        "skewness":-4.6326579476,
        "kurtosis":19.4623069512,
        "start_time":111.0,
        "end_time":119.0,
        "duration":9.0,
        "shaking_duration":4.0,
        "mean_gradient":0.0,
        "max_gradient":0.0,
        "weight_change":0.0
    },
    {
        "first_stop":5.0,
        "last_stop":284.0,
        "total_duration":135.0,
        "mean_of_mean_gradient":0.0032805708,
        "max_of_max_gradient":0.4920856229,
        "total_weight_change":0.9841712458,
        "skewness":-4.6326579476,
        "kurtosis":19.4623069512,
        "start_time":119.0,
        "end_time":127.0,
        "duration":9.0,
        "shaking_duration":5.0,
        "mean_gradient":0.0,
        "max_gradient":0.0,
        "weight_change":0.0
    },
    {
        "first_stop":5.0,
        "last_stop":284.0,
        "total_duration":135.0,
        "mean_of_mean_gradient":0.0032805708,
        "max_of_max_gradient":0.4920856229,
        "total_weight_change":0.9841712458,
        "skewness":-4.6326579476,
        "kurtosis":19.4623069512,
        "start_time":127.0,
        "end_time":136.0,
        "duration":10.0,
        "shaking_duration":5.0,
        "mean_gradient":0.0,
        "max_gradient":0.0,
        "weight_change":0.0
    },
    {
        "first_stop":5.0,
        "last_stop":284.0,
        "total_duration":135.0,
        "mean_of_mean_gradient":0.0032805708,
        "max_of_max_gradient":0.4920856229,
        "total_weight_change":0.9841712458,
        "skewness":-4.6326579476,
        "kurtosis":19.4623069512,
        "start_time":136.0,
        "end_time":146.0,
        "duration":11.0,
        "shaking_duration":4.0,
        "mean_gradient":0.0,
        "max_gradient":0.0,
        "weight_change":0.0
    },
    {
        "first_stop":5.0,
        "last_stop":284.0,
        "total_duration":135.0,
        "mean_of_mean_gradient":0.0032805708,
        "max_of_max_gradient":0.4920856229,
        "total_weight_change":0.9841712458,
        "skewness":-4.6326579476,
        "kurtosis":19.4623069512,
        "start_time":146.0,
        "end_time":155.0,
        "duration":10.0,
        "shaking_duration":5.0,
        "mean_gradient":0.0,
        "max_gradient":0.0,
        "weight_change":0.0
    },
    {
        "first_stop":5.0,
        "last_stop":284.0,
        "total_duration":135.0,
        "mean_of_mean_gradient":0.0032805708,
        "max_of_max_gradient":0.4920856229,
        "total_weight_change":0.9841712458,
        "skewness":-4.6326579476,
        "kurtosis":19.4623069512,
        "start_time":155.0,
        "end_time":164.0,
        "duration":10.0,
        "shaking_duration":5.0,
        "mean_gradient":0.0,
        "max_gradient":0.0,
        "weight_change":0.0
    },
    {
        "first_stop":5.0,
        "last_stop":284.0,
        "total_duration":135.0,
        "mean_of_mean_gradient":0.0032805708,
        "max_of_max_gradient":0.4920856229,
        "total_weight_change":0.9841712458,
        "skewness":-4.6326579476,
        "kurtosis":19.4623069512,
        "start_time":164.0,
        "end_time":177.0,
        "duration":14.0,
        "shaking_duration":5.0,
        "mean_gradient":0.0,
        "max_gradient":0.0,
        "weight_change":0.0
    },
    {
        "first_stop":5.0,
        "last_stop":284.0,
        "total_duration":135.0,
        "mean_of_mean_gradient":0.0032805708,
        "max_of_max_gradient":0.4920856229,
        "total_weight_change":0.9841712458,
        "skewness":-4.6326579476,
        "kurtosis":19.4623069512,
        "start_time":177.0,
        "end_time":187.0,
        "duration":11.0,
        "shaking_duration":5.0,
        "mean_gradient":0.0,
        "max_gradient":0.0,
        "weight_change":0.0
    },
    {
        "first_stop":5.0,
        "last_stop":284.0,
        "total_duration":135.0,
        "mean_of_mean_gradient":0.0032805708,
        "max_of_max_gradient":0.4920856229,
        "total_weight_change":0.9841712458,
        "skewness":-4.6326579476,
        "kurtosis":19.4623069512,
        "start_time":187.0,
        "end_time":195.0,
        "duration":9.0,
        "shaking_duration":4.0,
        "mean_gradient":0.0,
        "max_gradient":0.0,
        "weight_change":0.0
    },
    {
        "first_stop":5.0,
        "last_stop":284.0,
        "total_duration":135.0,
        "mean_of_mean_gradient":0.0032805708,
        "max_of_max_gradient":0.4920856229,
        "total_weight_change":0.9841712458,
        "skewness":-4.6326579476,
        "kurtosis":19.4623069512,
        "start_time":195.0,
        "end_time":204.0,
        "duration":10.0,
        "shaking_duration":5.0,
        "mean_gradient":0.0,
        "max_gradient":0.0,
        "weight_change":0.0
    },
    {
        "first_stop":5.0,
        "last_stop":284.0,
        "total_duration":135.0,
        "mean_of_mean_gradient":0.0032805708,
        "max_of_max_gradient":0.4920856229,
        "total_weight_change":0.9841712458,
        "skewness":-4.6326579476,
        "kurtosis":19.4623069512,
        "start_time":204.0,
        "end_time":221.0,
        "duration":18.0,
        "shaking_duration":9.0,
        "mean_gradient":0.0,
        "max_gradient":0.0,
        "weight_change":0.0
    },
    {
        "first_stop":5.0,
        "last_stop":284.0,
        "total_duration":135.0,
        "mean_of_mean_gradient":0.0032805708,
        "max_of_max_gradient":0.4920856229,
        "total_weight_change":0.9841712458,
        "skewness":-4.6326579476,
        "kurtosis":19.4623069512,
        "start_time":221.0,
        "end_time":238.0,
        "duration":18.0,
        "shaking_duration":10.0,
        "mean_gradient":0.0,
        "max_gradient":0.0,
        "weight_change":0.0
    },
    {
        "first_stop":5.0,
        "last_stop":284.0,
        "total_duration":135.0,
        "mean_of_mean_gradient":0.0032805708,
        "max_of_max_gradient":0.4920856229,
        "total_weight_change":0.9841712458,
        "skewness":-4.6326579476,
        "kurtosis":19.4623069512,
        "start_time":238.0,
        "end_time":248.0,
        "duration":11.0,
        "shaking_duration":7.0,
        "mean_gradient":0.0,
        "max_gradient":0.0,
        "weight_change":0.0
    },
    {
        "first_stop":5.0,
        "last_stop":284.0,
        "total_duration":135.0,
        "mean_of_mean_gradient":0.0032805708,
        "max_of_max_gradient":0.4920856229,
        "total_weight_change":0.9841712458,
        "skewness":-4.6326579476,
        "kurtosis":19.4623069512,
        "start_time":248.0,
        "end_time":264.0,
        "duration":17.0,
        "shaking_duration":6.0,
        "mean_gradient":0.0,
        "max_gradient":0.0,
        "weight_change":0.0
    },
    {
        "first_stop":5.0,
        "last_stop":284.0,
        "total_duration":135.0,
        "mean_of_mean_gradient":0.0032805708,
        "max_of_max_gradient":0.4920856229,
        "total_weight_change":0.9841712458,
        "skewness":-4.6326579476,
        "kurtosis":19.4623069512,
        "start_time":264.0,
        "end_time":284.0,
        "duration":21.0,
        "shaking_duration":11.0,
        "mean_gradient":0.0,
        "max_gradient":0.0,
        "weight_change":0.0
    },
    {
        "first_stop":5.0,
        "last_stop":284.0,
        "total_duration":135.0,
        "mean_of_mean_gradient":0.0032805708,
        "max_of_max_gradient":0.4920856229,
        "total_weight_change":0.9841712458,
        "skewness":-4.6326579476,
        "kurtosis":19.4623069512,
        "start_time":284.0,
        "end_time":290.0,
        "duration":7.0,
        "shaking_duration":7.0,
        "mean_gradient":0.0,
        "max_gradient":0.0,
        "weight_change":0.0
    }
]